DoodkeSP/Tests.py
DoodkeSP/__init__.py
DoodkeSP/addNewWorld.py
DoodkeSP/checkWord.py
DoodkeSP/main.py
DoodkeSP/randomWord.py
DoodkeSP/Keyboard/__init__.py
DoodkeSP/Keyboard/keyboardClickPos.py
DoodkeSP/Keyboard/keyboardMain.py
DoodkeSP/Keyboard/printKeyboard.py
DoodkeSP/Keyboard/printTextKeyboard.py
DoodkeSP/Menu/__init__.py
DoodkeSP/Menu/clickPosMenu.py
DoodkeSP/Menu/printTextMenu.py
DoodkeSP/Menu/startMenu.py
DoodkeSP-1.0.0.dist-info/LICENSE
DoodkeSP-1.0.0.dist-info/METADATA
DoodkeSP-1.0.0.dist-info/WHEEL
DoodkeSP-1.0.0.dist-info/top_level.txt
DoodkeSP-1.0.0.dist-info/RECORD
