Metadata-Version: 2.1
Name: DoodkeSP
Version: 1.0.0
Summary: My school project
Home-page: https://github.com/pypa/sampleproject
Author: David
Author-email: david@doodke.xyz
Project-URL: Bug Tracker, https://github.com/pypa/sampleproject/issues
Classifier: Programming Language :: Python :: 3
Classifier: License :: OSI Approved :: MIT License
Classifier: Operating System :: OS Independent
Requires-Python: >=3.6
License-File: LICENSE
